[
    "OK",
    "OK",
    "OK",
    "OK",
    "OK - ACK de fin",
    "{\n    \"supported_platforms\": [\n        {\n            \"platform\": \"Windows\",\n            \"game_count\": 9230\n        },\n        {\n            \"platform\": \"Mac\",\n            \"game_count\": 1773\n        },\n        {\n            \"platform\": \"Linux\",\n            \"game_count\": 1280\n        }\n    ],\n    \"generated_at\": \"2024-10-13T01:00:31.400046Z\"\n}",
    "{\n    \"top_10_indie_games_2010s\": [\n        {\n            \"rank\": 1,\n            \"name\": \"Beasts of Bermuda\",\n            \"average_playtime_hours\": 17147\n        },\n        {\n            \"rank\": 2,\n            \"name\": \"Revhead\",\n            \"average_playtime_hours\": 14716\n        },\n        {\n            \"rank\": 3,\n            \"name\": \"RimWorld\",\n            \"average_playtime_hours\": 10424\n        },\n        {\n            \"rank\": 4,\n            \"name\": \"Aberoth\",\n            \"average_playtime_hours\": 8334\n        },\n        {\n            \"rank\": 5,\n            \"name\": \"LOVE\\u00b3 -Love Cube-\",\n            \"average_playtime_hours\": 7259\n        },\n        {\n            \"rank\": 6,\n            \"name\": \"Franchise Hockey Manager 6\",\n            \"average_playtime_hours\": 4027\n        },\n        {\n            \"rank\": 7,\n            \"name\": \"Rento Fortune: Online Dice Board Game (\\u5927\\u5bcc\\u7fc1)\",\n            \"average_playtime_hours\": 3775\n        },\n        {\n            \"rank\": 8,\n            \"name\": \"Metaverse Keeper / \\u5143\\u80fd\\u5931\\u63a7\",\n            \"average_playtime_hours\": 2770\n        },\n        {\n            \"rank\": 9,\n            \"name\": \"In Exilium\",\n            \"average_playtime_hours\": 2716\n        },\n        {\n            \"rank\": 10,\n            \"name\": \"\\u592a\\u543e\\u7ed8\\u5377 The Scroll Of Taiwu\",\n            \"average_playtime_hours\": 2555\n        }\n    ],\n    \"generated_at\": \"2024-10-13T01:00:33.481461Z\"\n}",
    "{\"name\": \"Dead by Daylight\", \"count\": 31}",
    "{\"name\": \"Killing Floor 2\", \"count\": 31}",
    "{\"name\": \"Arma 3\", \"count\": 31}",
    "{\"name\": \"Miscreated\", \"count\": 31}",
    "{\"name\": \"Street Fighter V\", \"count\": 31}",
    "{\"name\": \"Far Cry 3\", \"count\": 31}",
    "{\"name\": \"Lords Of The Fallen\\u2122\", \"count\": 31}",
    "{\"name\": \"Aliens: Colonial Marines Collection\", \"count\": 31}",
    "{\"name\": \"Quake Live\\u2122\", \"count\": 31}",
    "{\"name\": \"SURVIVAL: Postapocalypse Now\", \"count\": 31}",
    "{\"name\": \"Surgeon Simulator\", \"count\": 31}",
    "{\"name\": \"Mirror's Edge\\u2122\", \"count\": 31}",
    "{\"name\": \"Gauntlet\\u2122 Slayer Edition\", \"count\": 31}",
    "{\"name\": \"DRAGON BALL XENOVERSE\", \"count\": 31}",
    "{\"name\": \"How to Survive\", \"count\": 31}",
    "{\"name\": \"Sniper Elite 3\", \"count\": 31}",
    "{\"name\": \"Grand Theft Auto: Episodes from Liberty City\", \"count\": 31}",
    "{\"name\": \"Yet Another Zombie Defense\", \"count\": 31}",
    "{\"name\": \"Portal 2\", \"count\": 31}",
    "{\"name\": \"Watch_Dogs\\u00ae 2\", \"count\": 31}",
    "{\"name\": \"Starpoint Gemini 2\", \"count\": 31}",
    "{\"game_id\": \"293180\", \"name\": \"Overcast - Walden and the Werewolf\", \"negative_count_percentile\": 32}",
    "{\"game_id\": \"234670\", \"name\": \"NARUTO SHIPPUDEN: Ultimate Ninja STORM 3 Full Burst HD\", \"negative_count_percentile\": 34}",
    "{\"game_id\": \"250900\", \"name\": \"The Binding of Isaac: Rebirth\", \"negative_count_percentile\": 38}",
    "{\"game_id\": \"285920\", \"name\": \"TerraTech\", \"negative_count_percentile\": 39}",
    "{\"game_id\": \"620\", \"name\": \"Portal 2\", \"negative_count_percentile\": 41}",
    "{\"game_id\": \"65790\", \"name\": \"ARMA: Cold War Assault\", \"negative_count_percentile\": 42}",
    "{\"game_id\": \"268750\", \"name\": \"Magicite\", \"negative_count_percentile\": 41}",
    "{\"game_id\": \"236150\", \"name\": \"Starpoint Gemini 2\", \"negative_count_percentile\": 45}",
    "{\"game_id\": \"10\", \"name\": \"Counter-Strike\", \"negative_count_percentile\": 43}",
    "{\"game_id\": \"270550\", \"name\": \"Yet Another Zombie Defense\", \"negative_count_percentile\": 50}",
    "{\"game_id\": \"238090\", \"name\": \"Sniper Elite 3\", \"negative_count_percentile\": 79}",
    "{\"game_id\": \"447040\", \"name\": \"Watch_Dogs\\u00ae 2\", \"negative_count_percentile\": 48}",
    "{\"game_id\": \"323470\", \"name\": \"DRAGON BALL XENOVERSE\", \"negative_count_percentile\": 90}",
    "{\"game_id\": \"12220\", \"name\": \"Grand Theft Auto: Episodes from Liberty City\", \"negative_count_percentile\": 77}",
    "{\"game_id\": \"17410\", \"name\": \"Mirror's Edge\\u2122\", \"negative_count_percentile\": 93}",
    "{\"game_id\": \"258970\", \"name\": \"Gauntlet\\u2122 Slayer Edition\", \"negative_count_percentile\": 87}",
    "{\"game_id\": \"351290\", \"name\": \"SURVIVAL: Postapocalypse Now\", \"negative_count_percentile\": 118}",
    "{\"game_id\": \"250400\", \"name\": \"How to Survive\", \"negative_count_percentile\": 93}",
    "{\"game_id\": \"49540\", \"name\": \"Aliens: Colonial Marines Collection\", \"negative_count_percentile\": 153}",
    "{\"game_id\": \"282440\", \"name\": \"Quake Live\\u2122\", \"negative_count_percentile\": 114}",
    "{\"game_id\": \"310950\", \"name\": \"Street Fighter V\", \"negative_count_percentile\": 210}",
    "{\"game_id\": \"233720\", \"name\": \"Surgeon Simulator\", \"negative_count_percentile\": 124}",
    "{\"game_id\": \"299740\", \"name\": \"Miscreated\", \"negative_count_percentile\": 224}",
    "{\"game_id\": \"265300\", \"name\": \"Lords Of The Fallen\\u2122\", \"negative_count_percentile\": 154}",
    "{\"game_id\": \"232090\", \"name\": \"Killing Floor 2\", \"negative_count_percentile\": 413}",
    "{\"game_id\": \"220240\", \"name\": \"Far Cry 3\", \"negative_count_percentile\": 219}",
    "{\"game_id\": \"107410\", \"name\": \"Arma 3\", \"negative_count_percentile\": 341}",
    "{\"game_id\": \"381210\", \"name\": \"Dead by Daylight\", \"negative_count_percentile\": 643}",
    "{\"name\": \"Counter-Strike\", \"count\": 31}",
    "{\"name\": \"ARMA: Cold War Assault\", \"count\": 31}",
    "{\"name\": \"Magicite\", \"count\": 31}",
    "{\"name\": \"TerraTech\", \"count\": 31}",
    "{\"name\": \"The Binding of Isaac: Rebirth\", \"count\": 31}",
    "{\"name\": \"DYNASTY WARRIORS 8: Xtreme Legends Complete Edition\", \"count\": 31}",
    "{\"name\": \"Canyon Capers\", \"count\": 31}",
    "{\"name\": \"NARUTO SHIPPUDEN: Ultimate Ninja STORM 3 Full Burst HD\", \"count\": 31}",
    "{\"name\": \"Overcast - Walden and the Werewolf\", \"count\": 31}",
    "{\n    \"top_5_indie_games_positive_reviews\": [\n        {\n            \"rank\": 1,\n            \"name\": \"The Plan\",\n            \"positive_review_count\": 831\n        },\n        {\n            \"rank\": 2,\n            \"name\": \"RimWorld\",\n            \"positive_review_count\": 642\n        },\n        {\n            \"rank\": 3,\n            \"name\": \"Surgeon Simulator\",\n            \"positive_review_count\": 631\n        },\n        {\n            \"rank\": 4,\n            \"name\": \"Darkest Dungeon\\u00ae\",\n            \"positive_review_count\": 537\n        },\n        {\n            \"rank\": 5,\n            \"name\": \"A Story About My Uncle\",\n            \"positive_review_count\": 501\n        }\n    ],\n    \"generated_at\": \"2024-10-13T01:03:07.985208Z\"\n}"
]